protokol/__init__.py
protokol/logger.py
protokol/protokol.py
protokol/settings.py
protokol/transports/__init__.py
protokol/transports/base.py
protokol/transports/nats.py
protokol/version.py
protokol-1.6.0.dist-info/LICENSE
protokol-1.6.0.dist-info/METADATA
protokol-1.6.0.dist-info/WHEEL
protokol-1.6.0.dist-info/RECORD
