Metadata-Version: 2.1
Name: protokol
Version: 1.6.0
Summary: NATS-oriented RPC and Event protocol
Home-page: https://github.com/event-driven-devs/protokol
Author: Sergey Zhegunya
Author-email: harmonicsseven@gmail.com
Maintainer: Ilia Abashin
Maintainer-email: abashinos@gmail.com
Requires-Python: >=3.7,<4.0
Classifier: Programming Language :: Python :: 3
Classifier: Programming Language :: Python :: 3.7
Classifier: Programming Language :: Python :: 3.8
Classifier: Programming Language :: Python :: 3.9
Classifier: Programming Language :: Python :: 3.10
Classifier: Programming Language :: Python :: 3.11
Requires-Dist: nats-py (>=2.2.0,<3.0.0)
Requires-Dist: tenacity (>=8.2.3,<9.0.0)
